sonatoki-0.11.2.dist-info/METADATA
sonatoki-0.11.2.dist-info/WHEEL
sonatoki-0.11.2.dist-info/entry_points.txt
sonatoki-0.11.2.dist-info/licenses/LICENSE
sonatoki/Cleaners.py
sonatoki/Configs.py
sonatoki/Filters.py
sonatoki/Preprocessors.py
sonatoki/Scorers.py
sonatoki/Tokenizers.py
sonatoki/__init__.py
sonatoki/__main__.py
sonatoki/alphabetic.txt
sonatoki/constants.py
sonatoki/ilo.py
sonatoki/linku.json
sonatoki/py.typed
sonatoki/sandbox.json
sonatoki/syllabic.txt
sonatoki/types.py
sonatoki/utils.py
sonatoki-0.11.2.dist-info/RECORD
