Metadata-Version: 2.1
Name: sonatoki
Version: 0.11.2
Summary: ilo li moku e toki li pana e sona ni: ni li toki ala toki pona?
Author-Email: "jan Kekan San (@gregdan3)" <gregory.danielson3@gmail.com>
License: AGPL-3.0-or-later
Requires-Python: >=3.8
Requires-Dist: unidecode>=1.3.6
Requires-Dist: regex>=2023.12.25
Requires-Dist: typing-extensions>=4.11.0
Requires-Dist: emoji>=2.12.1
